MANIFEST.in
setup.py
docs/HISTORY.txt
src/dolmen/__init__.py
src/dolmen.app.breadcrumbs.egg-info/PKG-INFO
src/dolmen.app.breadcrumbs.egg-info/SOURCES.txt
src/dolmen.app.breadcrumbs.egg-info/dependency_links.txt
src/dolmen.app.breadcrumbs.egg-info/namespace_packages.txt
src/dolmen.app.breadcrumbs.egg-info/not-zip-safe
src/dolmen.app.breadcrumbs.egg-info/requires.txt
src/dolmen.app.breadcrumbs.egg-info/top_level.txt
src/dolmen/app/__init__.py
src/dolmen/app/breadcrumbs/README.txt
src/dolmen/app/breadcrumbs/__init__.py
src/dolmen/app/breadcrumbs/configure.zcml
src/dolmen/app/breadcrumbs/crumbs.py
src/dolmen/app/breadcrumbs/ftesting.zcml
src/dolmen/app/breadcrumbs/tests.py
src/dolmen/app/breadcrumbs/url.py
src/dolmen/app/breadcrumbs/crumbs_templates/breadcrumbs.pt